{"cameraMode":{"drawMode":0,"name":"Shaded","section":"Shading Mode"},"sceneLighting":true,"audioPlay":false,"sceneViewState":{"m_AlwaysRefresh":false,"showFog":true,"showSkybox":true,"showFlares":true,"showImageEffects":true,"showParticleSystems":true,"showVisualEffectGraphs":true,"m_FxEnabled":true},"in2DMode":false,"pivot":{"x":0.5987842082977295,"y":0.6872341632843018,"z":-0.8985815048217773},"rotation":{"x":-0.05434394255280495,"y":0.9364372491836548,"z":-0.16780154407024384,"w":-0.30327308177948},"size":2.806558847427368,"orthographic":false}